notes_simple/__init__.py
notes_simple/server.py
notes_simple-0.1.0.dist-info/METADATA
notes_simple-0.1.0.dist-info/WHEEL
notes_simple-0.1.0.dist-info/entry_points.txt
notes_simple-0.1.0.dist-info/RECORD
