Metadata-Version: 2.4
Name: notes-simple
Version: 0.1.0
Summary: A MCP server project
Author-email: Darin <86675935+darinkishore@users.noreply.github.com>
Requires-Python: >=3.12
Requires-Dist: mcp>=1.1.0
